[
    {
        "model": "products.subcategory",
        "pk": 1,
        "fields": {
            "category": 2,
            "name": "Sweatshirt & Hoodies",
            "friendly_name": "Boys Sweatshirts",
            "description": "Warm and cozy options for boys."
        }
    },
    {
        "model": "products.subcategory",
        "pk": 2,
        "fields": {
            "category": 2,
            "name": "Jeans",
            "friendly_name": "Boys' Jeans",
            "description": "Durable and trendy jeans for boys."
        }
    },
    {
        "model": "products.subcategory",
        "pk": 3,
        "fields": {
            "category": 3,
            "name": "Frocks & Dresses",
            "friendly_name": "Girls Dresses",
            "description": "Beautiful dresses for girls."
        }
    },
    {
        "model": "products.subcategory",
        "pk": 4,
        "fields": {
            "category": 4,
            "name": "Casual Shoes",
            "friendly_name": "Footwear",
            "description": "Comfortable and stylish footwear."
        }
    },
    {
        "model": "products.subcategory",
        "pk": 5,
        "fields": {
            "category": 5,
            "name": "Clearance",
            "friendly_name": "Special Offers",
            "description": "Discounted and clearance items."
        }
    }
]


